{"cameraMode":{"drawMode":0,"name":"Shaded","section":"Shading Mode"},"sceneLighting":false,"audioPlay":false,"sceneViewState":{"m_AlwaysRefresh":false,"showFog":true,"showSkybox":false,"showFlares":true,"showImageEffects":true,"showParticleSystems":true,"showVisualEffectGraphs":true,"m_FxEnabled":true},"in2DMode":false,"pivot":{"x":0.0,"y":1.746999979019165,"z":0.0},"rotation":{"x":0.20482097566127778,"y":0.08064484596252442,"z":-0.016941767185926439,"w":0.9753033518791199},"size":0.9022750854492188,"orthographic":true}